pybls21/__init__.py
pybls21/client.py
pybls21/constants.py
pybls21/exceptions.py
pybls21/models.py
pybls21-4.0.3.dist-info/LICENSE
pybls21-4.0.3.dist-info/METADATA
pybls21-4.0.3.dist-info/WHEEL
pybls21-4.0.3.dist-info/top_level.txt
pybls21-4.0.3.dist-info/RECORD
