Metadata-Version: 2.1
Name: pybls21
Version: 4.0.3
Summary: An api allowing control of AC state (temperature, on/off, speed) of an Blauberg S21 device locally over TCP
Home-page: https://github.com/jvitkauskas/pybls21
Author: Julius Vitkauskas
Author-email: zadintuvas@gmail.com
Classifier: Programming Language :: Python :: 3
Classifier: License :: OSI Approved :: MIT License
Classifier: Operating System :: OS Independent
Requires-Python: >=3.8
License-File: LICENSE
Requires-Dist: pymodbus <4.0,>=3.6.3
